Products.LoginLockout-0.5.0-py2.7-nspkg.pth
Products/LoginLockout/__init__.py
Products/LoginLockout/config.py
Products/LoginLockout/configure.zcml
Products/LoginLockout/controlpanel.py
Products/LoginLockout/controlpanel.zcml
Products/LoginLockout/i18n.sh
Products/LoginLockout/interfaces.py
Products/LoginLockout/loginlockout_tool.py
Products/LoginLockout/patches.py
Products/LoginLockout/permissions.py
Products/LoginLockout/plugin.py
Products/LoginLockout/profiles.zcml
Products/LoginLockout/refresh.txt
Products/LoginLockout/setuphandlers.py
Products/LoginLockout/tests.py
Products/LoginLockout/upgrades.py
Products/LoginLockout/upgrades.zcml
Products/LoginLockout/version.txt
Products/LoginLockout/browser/__init__.py
Products/LoginLockout/browser/configure.zcml
Products/LoginLockout/browser/control.py
Products/LoginLockout/browser/loginlockout_history.pt
Products/LoginLockout/browser/loginlockout_last_password_changes.pt
Products/LoginLockout/browser/loginlockout_settings.pt
Products/LoginLockout/i18n/LoginLockout-es.po
Products/LoginLockout/i18n/LoginLockout-fr.po
Products/LoginLockout/i18n/LoginLockout-nl.po
Products/LoginLockout/i18n/LoginLockout.pot
Products/LoginLockout/i18n/manual.pot
Products/LoginLockout/profiles/default/browserlayer.xml
Products/LoginLockout/profiles/default/controlpanel.xml
Products/LoginLockout/profiles/default/import_steps.xml
Products/LoginLockout/profiles/default/loginlockout.txt
Products/LoginLockout/profiles/default/metadata.xml
Products/LoginLockout/profiles/default/propertiestool.xml
Products/LoginLockout/profiles/default/registry.xml
Products/LoginLockout/profiles/default/toolset.xml
Products/LoginLockout/profiles/uninstall/controlpanel.xml
Products/LoginLockout/profiles/uninstall/loginlockout_uninstall.txt
Products/LoginLockout/profiles/uninstall/propertiestool.xml
Products/LoginLockout/profiles/uninstall/registry.xml
Products/LoginLockout/profiles/uninstall/skins.xml
Products/LoginLockout/profiles/uninstall/toolset.xml
Products.LoginLockout-0.5.0.dist-info/METADATA
Products.LoginLockout-0.5.0.dist-info/WHEEL
Products.LoginLockout-0.5.0.dist-info/entry_points.txt
Products.LoginLockout-0.5.0.dist-info/namespace_packages.txt
Products.LoginLockout-0.5.0.dist-info/top_level.txt
Products.LoginLockout-0.5.0.dist-info/RECORD
