Metadata-Version: 2.1
Name: Products.LoginLockout
Version: 0.5.0
Summary: This Pluggable Authentication Service (PAS) plugin will lock a                  login after a predetermined number of incorrect attempts. Once                  locked, the user will be shown a page that tells them to contact                  their administrator to unlock.
Home-page: https://github.com/collective/Products.LoginLockout
Author: Dylan Jay
Author-email: software@pretaweb.com
License: GPL
Keywords: PAS Plugins Zope Login Lockout Plone security
Platform: UNKNOWN
Classifier: Development Status :: 4 - Beta
Classifier: Environment :: Plugins
Classifier: Environment :: Web Environment
Classifier: Framework :: Plone :: 4.3
Classifier: Framework :: Plone :: 5.0
Classifier: Framework :: Plone :: 5.1
Classifier: Framework :: Plone :: 5.2
Classifier: Framework :: Plone :: 6.0
Classifier: Framework :: Zope2
Classifier: Intended Audience :: System Administrators
Classifier: License :: OSI Approved :: BSD License
Classifier: Operating System :: OS Independent
Classifier: Programming Language :: Python
Classifier: Programming Language :: Python :: 2.7
Classifier: Programming Language :: Python :: 3.9
Classifier: Programming Language :: Python :: 3.10
Classifier: Programming Language :: Zope
Classifier: Topic :: Software Development :: Libraries :: Python Modules
Classifier: Topic :: System :: Systems Administration
Classifier: Topic :: System :: Systems Administration :: Authentication/Directory
Requires-Dist: setuptools
Requires-Dist: ipaddress
Requires-Dist: six
Requires-Dist: collective.monkeypatcher
Provides-Extra: test
Requires-Dist: plone.app.testing ; extra == 'test'
Requires-Dist: zope.testing ; extra == 'test'
